Sphinx_Nosejob-0.0.1.post0.dist-info/METADATA
Sphinx_Nosejob-0.0.1.post0.dist-info/RECORD
Sphinx_Nosejob-0.0.1.post0.dist-info/WHEEL
Sphinx_Nosejob-0.0.1.post0.dist-info/entry_points.txt
Sphinx_Nosejob-0.0.1.post0.dist-info/top_level.txt
sphinxcontrib/__init__.py
sphinxcontrib/nosejob/__init__.py
sphinxcontrib/nosejob/__main__.py
sphinxcontrib/nosejob/__meta__.py
sphinxcontrib/nosejob/database.merge.daba.py
sphinxcontrib/nosejob/database.merge.database.py
sphinxcontrib/nosejob/database.py
sphinxcontrib/nosejob/epilog.py
sphinxcontrib/nosejob/epilog.rst
sphinxcontrib/nosejob/pypi.py
sphinxcontrib/nosejob/tikzkit/__init__.py
sphinxcontrib/nosejob/tikzkit/__meta__.py
sphinxcontrib/nosejob/tikzkit/directives.py
sphinxcontrib/nosejob/tikzkit/nodes.py
sphinxcontrib/nosejob/tikzkit/reader.py
sphinxcontrib/nosejob/tikzkit/readers.py
sphinxcontrib/nosejob/tikzkit/utils.py
sphinxcontrib/nosejob/tikzkit/writer.py
sphinxcontrib/nosejob/tikzkit/writers.py
sphinxcontrib/nosejob/tikzkit/testing/test_dimensions.py
sphinxcontrib/nosejob/trees/__init__.py
sphinxcontrib/nosejob/trees/__meta__.py
sphinxcontrib/nosejob/trees/directives.py
sphinxcontrib/nosejob/trees/nodes.py
tests/__init__.py
tests/conftest.py
tests/testTrees.tmp
tests/test_trees.py
tests/documents/test-documents/conf.py
tests/documents/test-documents/trees.rst
tests/documents/test-trees/conf.py
tests/documents/test-trees/index.rst
