Metadata-Version: 2.1
Name: Sphinx-Nosejob
Version: 0.0.1.post0
Summary: Where masonry meets rhinoplasty
Home-page: http://www.manaikan.com/
Author: Carel van Dam
Author-email: carelvdam@gmail.com
License: UNKNOWN
Platform: UNKNOWN
Provides-Extra: tests
Requires-Dist: docutils
Requires-Dist: sphinx
Provides-Extra: tests
Requires-Dist: pytest; extra == 'tests'
Requires-Dist: beautifulsoup; extra == 'tests'
